gremlin_dsl/__init__.py
gremlin_dsl/core_dsl.py
gremlin_dsl-0.3.0.dist-info/LICENSE
gremlin_dsl-0.3.0.dist-info/WHEEL
gremlin_dsl-0.3.0.dist-info/METADATA
gremlin_dsl-0.3.0.dist-info/RECORD
