Metadata-Version: 2.1
Name: gremlin-dsl
Version: 0.3.0
Summary: A small example DSL using gremlinpython
License: MIT
Author: Elliot Hershberg
Author-email: eahershberg@gmail.com
Requires-Python: >=3.8,<4.0
Classifier: License :: OSI Approved :: MIT License
Classifier: Programming Language :: Python :: 3
Classifier: Programming Language :: Python :: 3.10
Classifier: Programming Language :: Python :: 3.8
Classifier: Programming Language :: Python :: 3.9
Requires-Dist: gremlinpython (>=3.6.0,<4.0.0)
